common_interfaces/ProcessInventory.py
common_interfaces/RedisManager.py
common_interfaces/S3Manager.py
common_interfaces/__init__.py
common_interfaces-0.1.2.dist-info/LICENSE
common_interfaces-0.1.2.dist-info/METADATA
common_interfaces-0.1.2.dist-info/WHEEL
common_interfaces-0.1.2.dist-info/top_level.txt
common_interfaces-0.1.2.dist-info/RECORD
