Metadata-Version: 2.1
Name: common-interfaces
Version: 0.1.2
Summary: Useful tools to work with ETL Redis config in Python
Home-page: https://github.com/rajumonpk/common_interfaces
Author: Rajendran
Author-email: rajumonpk@hotmail.com
License: MIT
Download-URL: https://pypi.org/project/common_interfaces/
Platform: UNKNOWN
Requires-Dist: redis (==3.5.3)
Requires-Dist: rq
